KTextTool/FE.py
KTextTool/__init__.py
KTextTool/analyze.py
KTextTool/preProcess.py
KTextTool-0.0.3.dist-info/LICENSE
KTextTool-0.0.3.dist-info/METADATA
KTextTool-0.0.3.dist-info/WHEEL
KTextTool-0.0.3.dist-info/top_level.txt
KTextTool-0.0.3.dist-info/RECORD
