Metadata-Version: 2.1
Name: KTextTool
Version: 0.0.3
Summary: For basic ML and text analyze
Home-page: https://github.com/Hipkevin/KText
Author: Kevin
License: UNKNOWN
Platform: UNKNOWN
Classifier: Programming Language :: Python :: 3
Classifier: License :: OSI Approved :: MIT License
Classifier: Operating System :: OS Independent
Requires-Python: >=3.6
